mazbot/__init__.py
mazbot/__main__.py
mazbot/runner.py
mazbot/conf/__init__.py
mazbot/conf/logging_conf.py
mazbot/enums/__init__.py
mazbot/enums/command.py
mazbot/enums/facing.py
mazbot/robot/__init__.py
mazbot/robot/robot.py
mazbot/robot/table.py
mazbot/utils/__init__.py
mazbot/utils/file_reader.py
mazbot-0.1.7.dist-info/AUTHORS.rst
mazbot-0.1.7.dist-info/LICENSE
mazbot-0.1.7.dist-info/METADATA
mazbot-0.1.7.dist-info/WHEEL
mazbot-0.1.7.dist-info/entry_points.txt
mazbot-0.1.7.dist-info/top_level.txt
mazbot-0.1.7.dist-info/RECORD
