Metadata-Version: 2.1
Name: mazbot
Version: 0.1.7
Summary: Control Bot in a grid without self-destructing
Home-page: https://github.com/flatwhitecuppa/mazbot
Author: Flat White
Author-email: flatwhitecuppa@gmail.com
License: MIT license
Keywords: mazbot
Platform: UNKNOWN
Classifier: Development Status :: 2 - Pre-Alpha
Classifier: Intended Audience :: Developers
Classifier: License :: OSI Approved :: MIT License
Classifier: Natural Language :: English
Classifier: Programming Language :: Python :: 3
Classifier: Programming Language :: Python :: 3.5
Classifier: Programming Language :: Python :: 3.6
Classifier: Programming Language :: Python :: 3.7
Classifier: Programming Language :: Python :: 3.8
Requires-Python: >=3.5
Requires-Dist: Click (>=7.0)
